gh_unwatch_except.py
gh_unwatch_except-0.0.1.dist-info/LICENSE
gh_unwatch_except-0.0.1.dist-info/METADATA
gh_unwatch_except-0.0.1.dist-info/WHEEL
gh_unwatch_except-0.0.1.dist-info/entry_points.txt
gh_unwatch_except-0.0.1.dist-info/top_level.txt
gh_unwatch_except-0.0.1.dist-info/RECORD
