Metadata-Version: 2.1
Name: gh-unwatch-except
Version: 0.0.1
Summary: A small utility for unwatching GitHub repositories.
Home-page: UNKNOWN
Author: Saimon Rai
License: UNKNOWN
Platform: UNKNOWN
License-File: LICENSE
Requires-Dist: click
Requires-Dist: PyGithub
